Manuales/__init__.py
populy/__init__.py
populy/functions.py
populy/individual.py
populy/plot.py
populy/plots.py
populy/population.py
populy/superpop.py
Populy-0.5.1.dist-info/LICENSE
Populy-0.5.1.dist-info/METADATA
Populy-0.5.1.dist-info/WHEEL
Populy-0.5.1.dist-info/top_level.txt
Populy-0.5.1.dist-info/RECORD
