Metadata-Version: 2.1
Name: Populy
Version: 0.5.1
Summary: Simulate forward time population genetics evolution with Python
Download-URL: https://github.com/R-mario/populy/
Author: Mario Ruiz Pérez
Author-email: marioruizperez00@gmail.com
License: MIT License
Keywords: python,evolution,population
Classifier: Programming Language :: Python :: 3
Classifier: License :: OSI Approved :: MIT License
License-File: LICENSE
